.gitignore
.travis.yml
CHANGES.txt
LICENSE.txt
README.txt
setup.py
tox.ini
upgrade-resources.sh
js/__init__.py
js.jquery_sortable.egg-info/PKG-INFO
js.jquery_sortable.egg-info/SOURCES.txt
js.jquery_sortable.egg-info/dependency_links.txt
js.jquery_sortable.egg-info/entry_points.txt
js.jquery_sortable.egg-info/namespace_packages.txt
js.jquery_sortable.egg-info/not-zip-safe
js.jquery_sortable.egg-info/requires.txt
js.jquery_sortable.egg-info/top_level.txt
js/jquery_sortable/__init__.py
js/jquery_sortable/test_jquery_sortable.txt
js/jquery_sortable/resources/jquery-sortable-min.js
js/jquery_sortable/resources/jquery-sortable.js